LocalCat/Translate.py
LocalCat/__init__.py
LocalCat/__version__.py
LocalCat/Translate/Local.py
LocalCat/Translate/Translate.py
LocalCat/Translate/__init__.py
localcat-0.0.10.dist-info/LICENSE.txt
localcat-0.0.10.dist-info/METADATA
localcat-0.0.10.dist-info/WHEEL
localcat-0.0.10.dist-info/top_level.txt
localcat-0.0.10.dist-info/RECORD
