Metadata-Version: 2.1
Name: localcat
Version: 0.0.10
Summary: Fine-tune Large Language Models locally.
Author-email: Ewen Wang <wang.enqun@outlook.com>
License: MIT License
Project-URL: Homepage, https://github.com/Ewen2015/LocalCat
Project-URL: Documentation, https://localcat.readthedocs.io
Project-URL: Repository, https://github.com/Ewen2015/LocalCat.git
Project-URL: Issues, https://github.com/Ewen2015/LocalCat/issues
Keywords: llm,finetune,ai,aws
Classifier: Programming Language :: Python :: 3.8
Classifier: License :: OSI Approved :: MIT License
Classifier: Operating System :: OS Independent
Requires-Python: >=3.8
License-File: LICENSE.txt
Requires-Dist: torch >=2.0
Requires-Dist: transformers ==4.30.2
Requires-Dist: datasets ==2.16.1
Requires-Dist: sentencepiece ==0.1.99
Requires-Dist: pydantic ==1.10.8
Requires-Dist: evaluate ==0.4.1
Requires-Dist: accelerate ==0.26.1
Requires-Dist: sacrebleu ==2.4.0
Requires-Dist: nltk ==3.8.1
Requires-Dist: tqdm ==4.64.1
Requires-Dist: boto3 ==1.34.38
Requires-Dist: sagemaker ==2.207.1
